<?xml version="1.0" encoding="UTF-8" standalone="no"?>
<tt xmlns:tt="http://www.w3.org/ns/ttml" xmlns:ttm="http://www.w3.org/ns/ttml#metadata" xmlns:ttp="http://www.w3.org/ns/ttml#parameter" xmlns:tts="http://www.w3.org/ns/ttml#styling" ttp:tickRate="10000000" ttp:timeBase="media" xmlns="http://www.w3.org/ns/ttml">
<head>
<ttp:profile use="http://netflix.com/ttml/profile/dfxp-ls-sdh"/>
<styling>
<style tts:color="white" tts:fontSize="100%" tts:fontWeight="normal" tts:textAlign="center" xml:id="defaultStyle"/>
<style tts:color="white" tts:fontSize="100%" tts:fontWeight="normal" tts:textAlign="center" xml:id="defaultStyle_1"/>
<style tts:color="white" tts:fontSize="100%" tts:fontStyle="italic" tts:fontWeight="normal" tts:textAlign="center" xml:id="defaultStyle_2"/>
</styling>
<layout>
<region tts:backgroundColor="transparent" tts:displayAlign="after" tts:extent="80.00% 80.00%" tts:origin="10.00% 10.00%" xml:id="region.after"/>
<region tts:backgroundColor="transparent" tts:displayAlign="before" tts:extent="80.00% 80.00%" tts:origin="10.00% 10.00%" xml:id="region.before"/>
</layout>
</head>
<body>
<div xml:space="preserve">
<p begin="495500003t" end="525530003t" region="region.after" style="defaultStyle" xml:id="subtitle0">Sorry about the hiccup, folks.<br/>Won't be long.</p>
<p begin="636475005t" end="656495005t" region="region.after" style="defaultStyle" xml:id="subtitle1">You got five minutes.</p>
<p begin="707380006t" end="763265001t" region="region.after" style="defaultStyle" xml:id="subtitle2">Howdy, folks. Could someone tell me<br/>if Mrs. Alma May Urbano is on board?</p>
<p begin="764935003t" end="785372503t" region="region.after" style="defaultStyle" xml:id="subtitle3">Alma May Urbano.</p>
<p begin="799975008t" end="815402503t" region="region.after" style="defaultStyle" xml:id="subtitle4">There you are.</p>
<p begin="817072506t" end="845015003t" region="region.after" style="defaultStyle" xml:id="subtitle5">Hello, dear, very good to meet you.</p>
<p begin="846685005t" end="895482503t" region="region.after" style="defaultStyle" xml:id="subtitle6">My name is Jimmy. I tried to visit you at<br/>Sandpiper, but they wouldn't allow me to.</p>
<p begin="897152506t" end="917590006t" region="region.after" style="defaultStyle" xml:id="subtitle7">Hey, you know what? It doesn't matter.</p>
<p begin="919260007t" end="956795005t" region="region.after" style="defaultStyle" xml:id="subtitle8">I saw your bus broken down,<br/>here you are, lucky me.</p>
<p begin="958465006t" end="1007680006t" region="region.after" style="defaultStyle" xml:id="subtitle9">Do you prefer to be called "Mrs. Urbano"<br/>or "Alma May" or just plain "Alma"?</p>
<p begin="1009350007t" end="1042292500t" region="region.after" style="defaultStyle" xml:id="subtitle10">My last name is McGill,<br/>but you can call me Jimmy.</p>
<p begin="1043962502t" end="1081080000t" region="region.after" style="defaultStyle" xml:id="subtitle11">Hey, everyone, my name<br/>is Jimmy McGill. I'm an attorney-at-law.</p>
<p begin="1082750001t" end="1129470007t" region="region.after" style="defaultStyle" xml:id="subtitle12">But don't mind me,<br/>just talk amongst yourselves.</p>
<p begin="1131130000t" end="1164917502t" region="region.after" style="defaultStyle" xml:id="subtitle13">Now, Alma May,<br/>do you recall responding to a mailer...</p>
<p begin="1166587505t" end="1209550007t" region="region.after" style="defaultStyle" xml:id="subtitle14">...from my law firm, Davis &amp; Main<br/>of Santa Fe, New Mexico?</p>
<p begin="1211210000t" end="1223725001t" region="region.after" style="defaultStyle" xml:id="subtitle15">I don't know.</p>
<p begin="1225395003t" end="1264600002t" region="region.after" style="defaultStyle" xml:id="subtitle16">Well, we were looking<br/>to help any Sandpiper residents...</p>
<p begin="1266270003t" end="1311310000t" region="region.after" style="defaultStyle" xml:id="subtitle17">...who may have been overcharged<br/>for basic goods and services.</p>
<p begin="1312980001t" end="1357612506t" region="region.after" style="defaultStyle" xml:id="subtitle18">-Now, does that ring a bell?<br/>-Maybe. Was it yellow?</p>
<p begin="1359700007t" end="1398070006t" region="region.after" style="defaultStyle" xml:id="subtitle19">It's canary yellow.<br/>I picked that color myself.</p>
<p begin="1399740007t" end="1434352502t" region="region.after" style="defaultStyle" xml:id="subtitle20">Well, ma'am, I'm here to make sure<br/>you get your money back.</p>
<p begin="1436022503t" end="1464800002t" region="region.after" style="defaultStyle" xml:id="subtitle21">What are you talking about?<br/>Who took Alma May's money?</p>
<p begin="1466887505t" end="1516937505t" region="region.after" style="defaultStyle" xml:id="subtitle22">Well, that's a very good question,<br/>and thank you for asking, Mr...?</p>
<p begin="1518607506t" end="1564482502t" region="region.after" style="defaultStyle" xml:id="subtitle23">-Amos. Amos Lydecker.<br/>-Mr. Lydecker, Jimmy McGill.</p>
<p begin="1566152503t" end="1607445005t" region="region.after" style="defaultStyle" xml:id="subtitle24">Now, nobody took<br/>anybody's money exactly, okay?</p>
<p begin="1609115006t" end="1655825003t" region="region.after" style="defaultStyle" xml:id="subtitle25">It's not like the Sandpiper people,<br/>you know, put on a ski mask...</p>
<p begin="1670427508t" end="1702117500t" region="region.after" style="defaultStyle" xml:id="subtitle26">...and mugged Alma May<br/>here at gunpoint.</p>
<p begin="1703787501t" end="1730905008t" region="region.after" style="defaultStyle" xml:id="subtitle27">So I want you to put<br/>that mental image out of your head.</p>
<p begin="1732565000t" end="1763430001t" region="region.after" style="defaultStyle" xml:id="subtitle28">See, what we're talking about here<br/>is just a discrepancy.</p>
<p begin="1765100002t" end="1820995008t" region="region.after" style="defaultStyle" xml:id="subtitle29">It's a little thing. It's fairly innocent,<br/>but we need to fix it.</p>
<p begin="1822655000t" end="1842257500t" region="region.after" style="defaultStyle" xml:id="subtitle30">You follow me?</p>
<p begin="1851442508t" end="1873540001t" region="region.after" style="defaultStyle" xml:id="subtitle31">Well, put it this way:</p>
<p begin="1875210002t" end="1906910003t" region="region.after" style="defaultStyle" xml:id="subtitle32">Alma May, let's say you're out<br/>on a date with your boyfriend.</p>
<p begin="1908580006t" end="1937775005t" region="region.after" style="defaultStyle" xml:id="subtitle33">You do have a boyfriend, right?<br/>You don't?</p>
<p begin="1939445006t" end="1975727502t" region="region.after" style="defaultStyle" xml:id="subtitle34">Come on, you--<br/>Alma May is holding out on me.</p>
<p begin="1985320002t" end="2027447505t" region="region.after" style="defaultStyle" xml:id="subtitle35">-Do you have a nephew?<br/>-Nephew? Yes. Steve.</p>
<p begin="2029117506t" end="2057060003t" region="region.after" style="defaultStyle" xml:id="subtitle36">-Okay, Steve. Is he a good guy?<br/>-Yeah, very good.</p>
<p begin="2058730006t" end="2100857508t" region="region.after" style="defaultStyle" xml:id="subtitle37">Okay. So let's say you<br/>and Steve go out to dinner at....</p>
<p begin="2102517500t" end="2133382500t" region="region.after" style="defaultStyle" xml:id="subtitle38">Well, Birdie's. That's where<br/>you're all headed today, right?</p>
<p begin="2135052502t" end="2150490007t" region="region.after" style="defaultStyle" xml:id="subtitle39">-Right.<br/>-All right.</p>
<p begin="2152150000t" end="2206375003t" region="region.after" style="defaultStyle" xml:id="subtitle40">So, both of you have a great meal.<br/>It's chicken-fried steak and green beans.</p>
<p begin="2208045005t" end="2236822503t" region="region.after" style="defaultStyle" xml:id="subtitle41">It's all perfect. Here comes the check.</p>
<p begin="2238492506t" end="2297300003t" region="region.after" style="defaultStyle" xml:id="subtitle42">"Hey, wait a doggone-- Twenty-four bucks<br/>for a side of buttermilk biscuits?"</p>
<p begin="2298970006t" end="2326495003t" region="region.after" style="defaultStyle" xml:id="subtitle43">-That doesn't sound right, now doesn't it?<br/>-No.</p>
<p begin="2328165005t" end="2374457501t" region="region.after" style="defaultStyle" xml:id="subtitle44">No, it does not. It sounds<br/>like something got added up wrong.</p>
<p begin="2376962503t" end="2411167508t" region="region.after" style="defaultStyle" xml:id="subtitle45">Well, naturally, you send your nephew,<br/>Steve, to talk to the manager...</p>
<p begin="2412827500t" end="2437857505t" region="region.after" style="defaultStyle" xml:id="subtitle46">...and, naturally, the manager<br/>corrects the mistake.</p>
<p begin="2439527506t" end="2485820002t" region="region.after" style="defaultStyle" xml:id="subtitle47">And what's more, he gives you a coupon<br/>for a free meal next time you come in.</p>
<p begin="2487490003t" end="2510850007t" region="region.after" style="defaultStyle" xml:id="subtitle48">-How about that?<br/>-Good.</p>
<p begin="2512510000t" end="2550890007t" region="region.after" style="defaultStyle" xml:id="subtitle49">Well, same kind of thing is what<br/>happened at Sandpiper Crossing.</p>
<p begin="2577580003t" end="2597182503t" region="region.after" style="defaultStyle" xml:id="subtitle50">And nothing...</p>
<p begin="2598852506t" end="2649320006t" region="region.after" style="defaultStyle" xml:id="subtitle51">...makes me sadder than to see people<br/>of the Greatest Generation...</p>
<p begin="2650990007t" end="2685185001t" region="region.after" style="defaultStyle" xml:id="subtitle52">...people like my own Nana<br/>and Bobo...</p>
<p begin="2693107500t" end="2723137500t" region="region.after" style="defaultStyle" xml:id="subtitle53">...getting overcharged<br/>by some great big company...</p>
<p begin="2724807501t" end="2752342508t" region="region.after" style="defaultStyle" xml:id="subtitle54">...even if it was an accident.</p>
<p begin="2760682507t" end="2793207500t" region="region.after" style="defaultStyle" xml:id="subtitle55">Now, I know that the good people<br/>at Sandpiper...</p>
<p begin="2794877501t" end="2817402503t" region="region.after" style="defaultStyle" xml:id="subtitle56">...wanna make this right,<br/>sooner or later.</p>
<p begin="2819072506t" end="2831170007t" region="region.after" style="defaultStyle" xml:id="subtitle57">But you know what?</p>
<p begin="2832830000t" end="2869122506t" region="region.after" style="defaultStyle" xml:id="subtitle58">Well, sometimes it's just easier...</p>
<p begin="2870792507t" end="2925842502t" region="region.after" style="defaultStyle" xml:id="subtitle59">...if you get your nephew, Steve,<br/>to go take care of it for you.</p>
<p begin="2927512503t" end="2968805005t" region="region.after" style="defaultStyle" xml:id="subtitle60">And that's how I want you<br/>to think of me.</p>
<p begin="2977980003t" end="3004670001t" region="region.after" style="defaultStyle" xml:id="subtitle61">Georgiana. Hey, there, Georgie girl.</p>
<p begin="3006340002t" end="3033865000t" region="region.after" style="defaultStyle" xml:id="subtitle62">Thank you. Oh, it's all there,<br/>everything I need.</p>
<p begin="3035535001t" end="3059312506t" region="region.after" style="defaultStyle" xml:id="subtitle63">Thank you so much. Enjoy your lunch.</p>
<p begin="3060982507t" end="3103935000t" region="region.after" style="defaultStyle" xml:id="subtitle64">Alma May, you did it.<br/>Thank you so much. Thank you.</p>
<p begin="3112285008t" end="3145227501t" region="region.after" style="defaultStyle" xml:id="subtitle65">Thank you, Henry. All right.</p>
<p begin="3146897502t" end="3173587500t" region="region.after" style="defaultStyle" xml:id="subtitle66">Hey, Sue. Okay.</p>
<p begin="3175257501t" end="3203617500t" region="region.after" style="defaultStyle" xml:id="subtitle67">Beautiful penmanship, a lost art.</p>
<p begin="3406322502t" end="3433847500t" region="region.after" style="defaultStyle" xml:id="subtitle68">Schweikart &amp; Cokely are pursuing<br/>an aggressive strategy...</p>
<p begin="3435517501t" end="3476810002t" region="region.before" style="defaultStyle_1" xml:id="subtitle69">...but looking at the relevant case law,<br/>it won't play with this magistrate judge.</p>
<p begin="3478480003t" end="3521860007t" region="region.after" style="defaultStyle" xml:id="subtitle70">I've read over a dozen of her rulings, all<br/>of which have sided with the plaintiff...</p>
<p begin="3523519999t" end="3540210006t" region="region.before" style="defaultStyle_1" xml:id="subtitle71">...on cases like this.</p>
<p begin="3541880007t" end="3586920002t" region="region.before" style="defaultStyle_1" xml:id="subtitle72">I've included a memo to that effect,<br/>which you can peruse at your leisure.</p>
<p begin="3588590003t" end="3600687506t" region="region.before" style="defaultStyle_1" xml:id="subtitle73">Thanks, Erin.</p>
<p begin="3602357508t" end="3634465000t" region="region.before" style="defaultStyle_1" xml:id="subtitle74">How about we move on<br/>to client outreach?</p>
<p begin="3661582507t" end="3678262503t" region="region.before" style="defaultStyle_1" xml:id="subtitle75">Jimmy?</p>
<p begin="3689942506t" end="3707457502t" region="region.before" style="defaultStyle_1" xml:id="subtitle76">You still with us?</p>
<p begin="3714127500t" end="3734147500t" region="region.before" style="defaultStyle_1" xml:id="subtitle77">I'm gonna save you<br/>from having to brag.</p>
<p begin="3735817501t" end="3766682502t" region="region.before" style="defaultStyle_1" xml:id="subtitle78">Over 200 new Sandpiper clients<br/>signed over the past three weeks.</p>
<p begin="3768352503t" end="3801305006t" region="region.before" style="defaultStyle_1" xml:id="subtitle79">-Well done, Jimmy.<br/>-Thank you. Thanks, Cliff.</p>
<p begin="3802975008t" end="3842180007t" region="region.before" style="defaultStyle_1" xml:id="subtitle80">Right now we're in the process<br/>of mapping out the entire Southwest...</p>
<p begin="3843839999t" end="3876792502t" region="region.before" style="defaultStyle_1" xml:id="subtitle81">...targeting the largest<br/>Sandpiper facilities first:</p>
<p begin="3878462503t" end="3909745005t" region="region.before" style="defaultStyle_1" xml:id="subtitle82">Phoenix, Colorado Springs,<br/>Fort Worth, Provo.</p>
<p begin="3911415006t" end="3930182506t" region="region.before" style="defaultStyle_1" xml:id="subtitle83">That's just for starters.</p>
<p begin="3931852507t" end="3967300002t" region="region.before" style="defaultStyle_1" xml:id="subtitle84">Ideally, my goal:<br/>another 200 by the end of the month.</p>
<p begin="3968970003t" end="4009845005t" region="region.before" style="defaultStyle_1" xml:id="subtitle85">With this many folks, we have an excellent<br/>shot at a solid batch of plaintiffs...</p>
<p begin="4011515006t" end="4040710006t" region="region.before" style="defaultStyle_1" xml:id="subtitle86">-...for the classes in each district.<br/>-Excellent.</p>
<p begin="4042380007t" end="4066565001t" region="region.before" style="defaultStyle_1" xml:id="subtitle87">Look forward to the next report.</p>
<p begin="4068235003t" end="4099517505t" region="region.before" style="defaultStyle_1" xml:id="subtitle88">On to a stickier wicket,<br/>coordinating actions.</p>
<p begin="4101187506t" end="4157907502t" region="region.before" style="defaultStyle_1" xml:id="subtitle89">Sorry, before we move on, I'd like to go<br/>back to client outreach just for a moment.</p>
<p begin="4159995005t" end="4205035000t" region="region.before" style="defaultStyle_1" xml:id="subtitle90">Looking over these numbers here,<br/>really astonishing results, Jimmy.</p>
<p begin="4206705001t" end="4221307506t" region="region.before" style="defaultStyle_1" xml:id="subtitle91">Incredible.</p>
<p begin="4227977502t" end="4270940006t" region="region.before" style="defaultStyle_1" xml:id="subtitle92">Your last trip to Amarillo,<br/>you came back with 22 new clients.</p>
<p begin="4272610007t" end="4293047508t" region="region.after" style="defaultStyle" xml:id="subtitle93">-Twenty-four.<br/>-Twenty-four.</p>
<p begin="4295125000t" end="4312650007t" region="region.before" style="defaultStyle_1" xml:id="subtitle94">I'm confused.</p>
<p begin="4314310000t" end="4358107502t" region="region.before" style="defaultStyle_1" xml:id="subtitle95">How many people out there<br/>actually responded to our direct mailer?</p>
<p begin="4361865006t" end="4376457501t" region="region.after" style="defaultStyle" xml:id="subtitle96">One.</p>
<p begin="4392312507t" end="4411915006t" region="region.before" style="defaultStyle_1" xml:id="subtitle97">Oh, right. Yeah.</p>
<p begin="4413585008t" end="4441945006t" region="region.before" style="defaultStyle_1" xml:id="subtitle98">A Mrs. Alma May Urbano.</p>
<p begin="4450285005t" end="4502422507t" region="region.before" style="defaultStyle_1" xml:id="subtitle99">But you got 24 new clients<br/>from this one response?</p>
<p begin="4507422502t" end="4529530003t" region="region.before" style="defaultStyle_1" xml:id="subtitle100">That is....</p>
<p begin="4534122508t" end="4542462507t" region="region.before" style="defaultStyle_1" xml:id="subtitle101">Wow.</p>
<p begin="4546210001t" end="4572910007t" region="region.before" style="defaultStyle_1" xml:id="subtitle102">Well, you're welcome.<br/>I mean, what, is there a problem?</p>
<p begin="4574570000t" end="4618785003t" region="region.before" style="defaultStyle_1" xml:id="subtitle103">Well, might not some parties,<br/>the opposing counsel, for example...</p>
<p begin="4620455005t" end="4640892506t" region="region.after" style="defaultStyle" xml:id="subtitle104">...see this differential and conclude...</p>
<p begin="4642562507t" end="4672592507t" region="region.after" style="defaultStyle" xml:id="subtitle105">...that there may have been<br/>some solicitation involved?</p>
<p begin="4674262508t" end="4690107505t" region="region.after" style="defaultStyle" xml:id="subtitle106">-I did not solicit.<br/>-I'm wondering...</p>
<p begin="4691777506t" end="4710962506t" region="region.after" style="defaultStyle" xml:id="subtitle107">...how you account for your success...</p>
<p begin="4712632507t" end="4749750003t" region="region.after" style="defaultStyle" xml:id="subtitle108">...because it will definitely raise<br/>eyebrows over at Schweikart &amp; Cokely.</p>
<p begin="4759342503t" end="4779780003t" region="region.before" style="defaultStyle_1" xml:id="subtitle109">I'm sorry, but it will.</p>
<p begin="4781450006t" end="4811480006t" region="region.before" style="defaultStyle_1" xml:id="subtitle110">Particularly in a case<br/>involving seniors...</p>
<p begin="4813150007t" end="4844432508t" region="region.before" style="defaultStyle_1" xml:id="subtitle111">...for whom the ethical guidelines<br/>on solicitation...</p>
<p begin="4846092500t" end="4868200002t" region="region.before" style="defaultStyle_1" xml:id="subtitle112">...were virtually created by the ABA.</p>
<p begin="4869870003t" end="4896560001t" region="region.after" style="defaultStyle" xml:id="subtitle113">Chuck, I'm sure that--</p>
<p begin="4909910003t" end="4951202506t" region="region.after" style="defaultStyle" xml:id="subtitle114">Jimmy, if you could clear this up,<br/>that would be helpful.</p>
<p begin="4952872507t" end="5002922507t" region="region.after" style="defaultStyle" xml:id="subtitle115">I went to Amarillo to confer<br/>with a client and to make sure...</p>
<p begin="5004592508t" end="5057137501t" region="region.after" style="defaultStyle" xml:id="subtitle116">...that we had a solid, good-faith basis<br/>for our case there, overall.</p>
<p begin="5058807502t" end="5104692508t" region="region.after" style="defaultStyle" xml:id="subtitle117">As many of you are aware, I've visited<br/>more than my share of retirement homes.</p>
<p begin="5106352500t" end="5122207506t" region="region.after" style="defaultStyle" xml:id="subtitle118">These are close-knit communities.</p>
<p begin="5123877508t" end="5147645001t" region="region.after" style="defaultStyle" xml:id="subtitle119">Let me tell you,<br/>word gets around real fast.</p>
<p begin="5149315003t" end="5196860001t" region="region.after" style="defaultStyle" xml:id="subtitle120">If Dorothy in Phase 2 gets<br/>a new Rascal scooter, it's big news.</p>
<p begin="5198530002t" end="5223560007t" region="region.after" style="defaultStyle" xml:id="subtitle121">So these other 23 residents,<br/>they approached you?</p>
<p begin="5224812508t" end="5263600007t" region="region.after" style="defaultStyle" xml:id="subtitle122">Cliff, they heard the scuttlebutt<br/>before I crossed state lines.</p>
<p begin="5265260000t" end="5295290000t" region="region.after" style="defaultStyle" xml:id="subtitle123">And I certainly didn't have<br/>to go knocking on any doors.</p>
<p begin="5299882503t" end="5326990001t" region="region.after" style="defaultStyle" xml:id="subtitle124">And is it any surprise<br/>that they wanna speak with a guy...</p>
<p begin="5328660002t" end="5359525003t" region="region.after" style="defaultStyle" xml:id="subtitle125">...who was there to show them<br/>they may have money coming their way?</p>
<p begin="5368282502t" end="5395807500t" region="region.after" style="defaultStyle" xml:id="subtitle126">I gotta tell you, with all that in mind...</p>
<p begin="5397477501t" end="5418750002t" region="region.after" style="defaultStyle" xml:id="subtitle127">...I should've done better.</p>
<p begin="5428760002t" end="5455450000t" region="region.after" style="defaultStyle" xml:id="subtitle128">Makes sense. Howard?</p>
<p begin="5466295000t" end="5482985006t" region="region.after" style="defaultStyle" xml:id="subtitle129">Chuck?</p>
<p begin="5491325005t" end="5508005001t" region="region.after" style="defaultStyle" xml:id="subtitle130">We good to move on?</p>
<p begin="5542627506t" end="5568482502t" region="region.after" style="defaultStyle" xml:id="subtitle131">And, Chuck, not incidentally,<br/>it is absolutely vital...</p>
<p begin="5570152503t" end="5614367508t" region="region.after" style="defaultStyle" xml:id="subtitle132">...that we dot our I's and cross<br/>our T's here. Invaluable. So, thank you.</p>
<p begin="5616027500t" end="5643562507t" region="region.after" style="defaultStyle" xml:id="subtitle133">Well, the price of excellence<br/>is eternal vigilance.</p>
<p begin="5645232508t" end="5658572502t" region="region.after" style="defaultStyle" xml:id="subtitle134">Indeed.</p>
<p begin="5678175001t" end="5705292508t" region="region.after" style="defaultStyle" xml:id="subtitle135">Coordination.<br/>I believe that's where we left off.</p>
<p begin="5706952500t" end="5741992506t" region="region.after" style="defaultStyle" xml:id="subtitle136">That's right. Brian, this is your thing,<br/>so why don't you take this?</p>
<p begin="5743662507t" end="5777857501t" region="region.after" style="defaultStyle" xml:id="subtitle137">Sure. Considering the dimensions<br/>of these cases...</p>
<p begin="5779527502t" end="5819567502t" region="region.after" style="defaultStyle" xml:id="subtitle138">...taken together and individually,<br/>it makes sense to designate someone...</p>
<p begin="5821237505t" end="5839170002t" region="region.after" style="defaultStyle" xml:id="subtitle139">...to handle the scheduling.</p>
<p begin="5840840003t" end="5880880003t" region="region.after" style="defaultStyle" xml:id="subtitle140">What I'm proposing is we create a small<br/>team at D&amp;M dedicated specifically...</p>
<p begin="5882550006t" end="5909657502t" region="region.after" style="defaultStyle" xml:id="subtitle141">...to coordinating all elements<br/>of the individual actions.</p>
<p begin="5911327505t" end="5958872502t" region="region.after" style="defaultStyle" xml:id="subtitle142">-We'll loop in HHM on anything--<br/>-I'm sorry. Excuse me for interrupting.</p>
<p begin="5960542503t" end="5998077501t" region="region.after" style="defaultStyle" xml:id="subtitle143">I just wanna say<br/>that I take Chuck's point, I do.</p>
<p begin="5999747502t" end="6036447500t" region="region.after" style="defaultStyle" xml:id="subtitle144">I mean, this is like<br/>a "wife of Caesar" type thing.</p>
<p begin="6038117501t" end="6071070003t" region="region.after" style="defaultStyle" xml:id="subtitle145">There can't even be a hint<br/>of solicitation...</p>
<p begin="6072740006t" end="6093595006t" region="region.after" style="defaultStyle" xml:id="subtitle146">...so I'm gonna pull back.</p>
<p begin="6096925000t" end="6138217501t" region="region.after" style="defaultStyle" xml:id="subtitle147">All right, no more meet-and-greets<br/>at Sandpiper facilities.</p>
<p begin="6139887502t" end="6165335008t" region="region.after" style="defaultStyle" xml:id="subtitle148">I'll find another way to proceed.</p>
<p begin="6166995000t" end="6187432500t" region="region.after" style="defaultStyle" xml:id="subtitle149">Well, Jimmy, we'll leave that up to you.</p>
<p begin="6189102502t" end="6209957502t" region="region.after" style="defaultStyle" xml:id="subtitle150">You know,<br/>client outreach is your department.</p>
<p begin="6214967508t" end="6233735006t" region="region.after" style="defaultStyle" xml:id="subtitle151">Where was I?</p>
<p begin="6235405008t" end="6251250003t" region="region.after" style="defaultStyle" xml:id="subtitle152">Okay, right.</p>
<p begin="6252920006t" end="6292960006t" region="region.after" style="defaultStyle" xml:id="subtitle153">If we have a more consolidated nerve<br/>center here in New Mexico, where the....</p>
<p begin="6368865001t" end="6398895001t" region="region.after" style="defaultStyle" xml:id="subtitle154">Hey, Kim, where can I get a copy<br/>of that Niederman deposition?</p>
<p begin="6400565003t" end="6431012503t" region="region.after" style="defaultStyle" xml:id="subtitle155">I've got an extra Niederman, Jimmy.<br/>You can have one of mine.</p>
<p begin="6432682506t" end="6457702500t" region="region.after" style="defaultStyle" xml:id="subtitle156">-Wow. Thanks, Erin.<br/>-No worries.</p>
<p begin="6465217508t" end="6499412502t" region="region.after" style="defaultStyle" xml:id="subtitle157">-Oh, shoot, where did I put that?<br/>-Thanks, that's....</p>
<p begin="6530277502t" end="6571570003t" region="region.after" style="defaultStyle" xml:id="subtitle158">Man, do you believe Chuck in there?<br/>Jesus, solicitation?</p>
<p begin="6573240006t" end="6596590000t" region="region.after" style="defaultStyle" xml:id="subtitle159">Let me tell you,<br/>when we were building this case...</p>
<p begin="6598260001t" end="6622455005t" region="region.after" style="defaultStyle" xml:id="subtitle160">...I was chasing down 80-year-old<br/>mall-walkers.</p>
<p begin="6624125006t" end="6665417508t" region="region.after" style="defaultStyle" xml:id="subtitle161">That was solicitation,<br/>but did he say "boo"? Bullshit, he did.</p>
<p begin="6667077500t" end="6689185001t" region="region.after" style="defaultStyle" xml:id="subtitle162">What happened in Texas?</p>
<p begin="6694195006t" end="6711710003t" region="region.after" style="defaultStyle" xml:id="subtitle163">Nothing.</p>
<p begin="6713380006t" end="6740070002t" region="region.after" style="defaultStyle" xml:id="subtitle164">-I did my job.<br/>-No song-and-dance in the day room...</p>
<p begin="6741740003t" end="6776769999t" region="region.after" style="defaultStyle" xml:id="subtitle165">-...for the old-timers?<br/>-No. No.</p>
<p begin="6778857501t" end="6813897506t" region="region.after" style="defaultStyle" xml:id="subtitle166">-Not in the day room.<br/>-Solicitation can get you disbarred.</p>
<p begin="6815567508t" end="6847257500t" region="region.after" style="defaultStyle" xml:id="subtitle167">-This matters.<br/>-Well, here's what I think matters:</p>
<p begin="6848927501t" end="6873540006t" region="region.after" style="defaultStyle" xml:id="subtitle168">Twenty-four senior citizens<br/>now have representation.</p>
<p begin="6875210007t" end="6900647502t" region="region.after" style="defaultStyle" xml:id="subtitle169">Before, they didn't know<br/>they were getting ripped off.</p>
<p begin="6902317505t" end="6942775005t" region="region.after" style="defaultStyle" xml:id="subtitle170">Now they have us in their corner.<br/>How is that not a win?</p>
<p begin="6944445006t" end="6970300002t" region="region.after" style="defaultStyle" xml:id="subtitle171">You said in there<br/>you'd find another way.</p>
<p begin="6971970003t" end="6989067501t" region="region.after" style="defaultStyle" xml:id="subtitle172">Did you mean it?</p>
<p begin="6990737502t" end="7027019999t" region="region.after" style="defaultStyle" xml:id="subtitle173">-Sure. Absolutely, I'll....<br/>-Oh, it's just....</p>
<p begin="7063312506t" end="7081662503t" region="region.after" style="defaultStyle" xml:id="subtitle174">Look, I....</p>
<p begin="7095430007t" end="7124625006t" region="region.after" style="defaultStyle" xml:id="subtitle175">I need you to understand something<br/>very critical here.</p>
<p begin="7126295008t" end="7137547500t" region="region.after" style="defaultStyle" xml:id="subtitle176">Shoot.</p>
<p begin="7156742508t" end="7183015005t" region="region.after" style="defaultStyle" xml:id="subtitle177">I put myself on the line<br/>to get you this job.</p>
<p begin="7198025000t" end="7236405008t" region="region.after" style="defaultStyle" xml:id="subtitle178">Okay. I thought it was because<br/>I'm sensational with old people.</p>
<p begin="7238065000t" end="7264347506t" region="region.after" style="defaultStyle" xml:id="subtitle179">Yeah, and who do you think<br/>told them that?</p>
<p begin="7266017508t" end="7311057502t" region="region.after" style="defaultStyle" xml:id="subtitle180">-So, what, you threw me a bone?<br/>-No, asshole.</p>
<p begin="7312727505t" end="7330660002t" region="region.after" style="defaultStyle" xml:id="subtitle181">You know I believe in you.</p>
<p begin="7347757500t" end="7371952503t" region="region.after" style="defaultStyle" xml:id="subtitle182">But then I made my beliefs known<br/>to them.</p>
<p begin="7373622506t" end="7401565003t" region="region.after" style="defaultStyle" xml:id="subtitle183">And now everything you do<br/>reflects back on me with Howard...</p>
<p begin="7403235005t" end="7437847500t" region="region.after" style="defaultStyle" xml:id="subtitle184">...because ultimately I talked him into<br/>going out on a limb for you too.</p>
<p begin="7455372507t" end="7492490003t" region="region.after" style="defaultStyle" xml:id="subtitle185">Do you understand?<br/>It's my word, it's my judgment.</p>
<p begin="7494160006t" end="7504587506t" region="region.after" style="defaultStyle" xml:id="subtitle186">Yeah.</p>
<p begin="7557549999t" end="7585920007t" region="region.after" style="defaultStyle" xml:id="subtitle187">You and I both know<br/>you can do this job.</p>
<p begin="7637222508t" end="7663495005t" region="region.after" style="defaultStyle" xml:id="subtitle188">But, please, you just have to do it right.</p>
<p begin="7771517502t" end="7830742502t" region="region.after" style="defaultStyle" xml:id="subtitle189">Yeah, you wanna make sure you<br/>put in the batteries the right way...</p>
<p begin="7832412503t" end="7848257500t" region="region.after" style="defaultStyle" xml:id="subtitle190">...or it won't work.</p>
<p begin="7849927501t" end="7898725000t" region="region.after" style="defaultStyle" xml:id="subtitle191">Then you close them up,<br/>and I think--</p>
<p begin="7902482503t" end="7930007501t" region="region.after" style="defaultStyle" xml:id="subtitle192">I think you're good to go, young lady.</p>
<p begin="7931677502t" end="7969630001t" region="region.after" style="defaultStyle" xml:id="subtitle193">Why don't you give his foot<br/>a squeeze?</p>
<p begin="8016350007t" end="8033447505t" region="region.after" style="defaultStyle" xml:id="subtitle194">He's funny.</p>
<p begin="8040117501t" end="8055555006t" region="region.after" style="defaultStyle" xml:id="subtitle195">Oh, darling.</p>
<p begin="8072652503t" end="8091837502t" region="region.after" style="defaultStyle" xml:id="subtitle196">I'm gonna name you...</p>
<p begin="8106022507t" end="8121032502t" region="region.after" style="defaultStyle" xml:id="subtitle197">...Mr. Snuggly.</p>
<p begin="8141052502t" end="8155655006t" region="region.after" style="defaultStyle" xml:id="subtitle198">Are you hungry?</p>
<p begin="8162742503t" end="8180675001t" region="region.after" style="defaultStyle" xml:id="subtitle199">I'm gonna get you some....</p>
<p begin="8182345003t" end="8206540007t" region="region.after" style="defaultStyle" xml:id="subtitle200">That should get you through<br/>to next month.</p>
<p begin="8221550002t" end="8238647500t" region="region.after" style="defaultStyle" xml:id="subtitle201">Mike, thank you.</p>
<p begin="8242405003t" end="8275775006t" region="region.after" style="defaultStyle" xml:id="subtitle202">-But you shouldn't feel that you need to--<br/>-Too late.</p>
<p begin="8329572500t" end="8347097508t" region="region.after" style="defaultStyle" xml:id="subtitle203">Something up?</p>
<p begin="8362525003t" end="8396312507t" region="region.after" style="defaultStyle" xml:id="subtitle204">-Feels like something is up.<br/>-No, it's....</p>
<p begin="8397982508t" end="8432595003t" region="region.after" style="defaultStyle" xml:id="subtitle205">-I didn't get much sleep. My head is....<br/>-I'm sorry.</p>
<p begin="8434265005t" end="8468052508t" region="region.after" style="defaultStyle" xml:id="subtitle206">You tell me it's none of my business,<br/>I'll drop it.</p>
<p begin="8469712500t" end="8506005006t" region="region.after" style="defaultStyle" xml:id="subtitle207">-I don't want you to worry.<br/>-Not the worrying kind.</p>
<p begin="8541452502t" end="8563977505t" region="region.after" style="defaultStyle" xml:id="subtitle208">Last two nights I heard gunshots.</p>
<p begin="8571900002t" end="8609435000t" region="region.after" style="defaultStyle" xml:id="subtitle209">First night, they were maybe a block<br/>or two over, woke me up.</p>
<p begin="8611105001t" end="8643640003t" region="region.after" style="defaultStyle" xml:id="subtitle210">My first thought was firecrackers.<br/>That's what I assumed at the time.</p>
<p begin="8645310006t" end="8670747501t" region="region.after" style="defaultStyle" xml:id="subtitle211">But then last night,<br/>there's no mistaking it.</p>
<p begin="8672417502t" end="8697030007t" region="region.after" style="defaultStyle" xml:id="subtitle212">There was three of them.<br/>They were quick: Pop, pop, pop.</p>
<p begin="8698690000t" end="8737070007t" region="region.after" style="defaultStyle" xml:id="subtitle213">Closer, like they were<br/>right outside the house.</p>
<p begin="8738730000t" end="8764177505t" region="region.after" style="defaultStyle" xml:id="subtitle214">-You call the cops?<br/>-Yeah.</p>
<p begin="8765847506t" end="8800877501t" region="region.after" style="defaultStyle" xml:id="subtitle215">Took them over an hour to get here,<br/>they looked around for two minutes...</p>
<p begin="8802547502t" end="8824237505t" region="region.after" style="defaultStyle" xml:id="subtitle216">...but by then<br/>there was nothing to see.</p>
<p begin="8849257500t" end="8885967506t" region="region.after" style="defaultStyle" xml:id="subtitle217">-I'm staying here tonight.<br/>-No. Mike, no, that's not necessary.</p>
<p begin="8887637508t" end="8949775000t" region="region.after" style="defaultStyle" xml:id="subtitle218">-It is not a problem. I'll take the couch.<br/>-Mike, you asked, so I answered.</p>
<p begin="8955620006t" end="8978562508t" region="region.after" style="defaultStyle" xml:id="subtitle219">Please, don't make me sorry I told you.</p>
<p begin="9032777502t" end="9051962502t" region="region.after" style="defaultStyle" xml:id="subtitle220">Kaylee, come.</p>
<p begin="9056137506t" end="9074487505t" region="region.after" style="defaultStyle" xml:id="subtitle221">Get your supper.</p>
<p begin="9250075000t" end="9277610007t" region="region.after" style="defaultStyle" xml:id="subtitle222">What about Colorado Springs?</p>
<p begin="9291367501t" end="9337670007t" region="region.after" style="defaultStyle" xml:id="subtitle223">Two hundred eighty-three residents,<br/>and we sent out 283 mailers.</p>
<p begin="9339330000t" end="9366865006t" region="region.after" style="defaultStyle" xml:id="subtitle224">Yeah, and how many response cards<br/>came back?</p>
<p begin="9369777500t" end="9398147508t" region="region.after" style="defaultStyle" xml:id="subtitle225">-Zero.<br/>-Zero?</p>
<p begin="9423585003t" end="9445275005t" region="region.after" style="defaultStyle" xml:id="subtitle226">Son of a bitch.</p>
<p begin="9450692500t" end="9486985006t" region="region.before" style="defaultStyle_1" xml:id="subtitle227">-Dana, Toni, have a good one.<br/>-You too, Mr. Main.</p>
<p begin="9488655008t" end="9516597506t" region="region.before" style="defaultStyle_1" xml:id="subtitle228">Cliff, could I have a second?</p>
<p begin="9518267508t" end="9553297502t" region="region.after" style="defaultStyle" xml:id="subtitle229">-What's up?<br/>-Yeah, it's the Sandpiper mailers.</p>
<p begin="9554967505t" end="9587502507t" region="region.after" style="defaultStyle" xml:id="subtitle230">We should be getting responses<br/>of, like, 12 to 15 percent...</p>
<p begin="9589172508t" end="9624202503t" region="region.after" style="defaultStyle" xml:id="subtitle231">...but we're getting ones and twos,<br/>in Colorado Springs, zero.</p>
<p begin="9625872506t" end="9642970002t" region="region.after" style="defaultStyle" xml:id="subtitle232">Wow. How can that be?</p>
<p begin="9647145006t" end="9660067500t" region="region.after" style="defaultStyle" xml:id="subtitle233">I'm thinking it's the staff.</p>
<p begin="9661737501t" end="9687185006t" region="region.after" style="defaultStyle" xml:id="subtitle234">They're tossing the mailers<br/>before they can reach the residents.</p>
<p begin="9688855008t" end="9718467508t" region="region.after" style="defaultStyle" xml:id="subtitle235">Maybe they got told to do it<br/>by the Sandpiper front office...</p>
<p begin="9720127500t" end="9739730000t" region="region.after" style="defaultStyle" xml:id="subtitle236">...which would be actionable as hell.</p>
<p begin="9741400001t" end="9769760000t" region="region.after" style="defaultStyle" xml:id="subtitle237">If we could prove it. Big "if."</p>
<p begin="9773517502t" end="9798965008t" region="region.after" style="defaultStyle" xml:id="subtitle238">And to do so would take<br/>more manpower than I can spare.</p>
<p begin="9800625000t" end="9826490006t" region="region.after" style="defaultStyle" xml:id="subtitle239">Let's just stick with<br/>getting those client numbers up.</p>
<p begin="9828160007t" end="9860685000t" region="region.after" style="defaultStyle" xml:id="subtitle240">-Guess you better think of another way.<br/>-I think I got it.</p>
<p begin="9862355001t" end="9884462503t" region="region.after" style="defaultStyle" xml:id="subtitle241">TV commercial, highly targeted.</p>
<p begin="9889055008t" end="9926172506t" region="region.after" style="defaultStyle" xml:id="subtitle242">Let me tell you,<br/>at Sandpiper the trains run on time.</p>
<p begin="9927842507t" end="9949115008t" region="region.after" style="defaultStyle" xml:id="subtitle243">Mussolini would be proud.</p>
<p begin="9950775000t" end="9982475001t" region="region.after" style="defaultStyle" xml:id="subtitle244">Everyone I've visited so far,<br/>same exact schedule.</p>
<p begin="9984145003t" end="10020427500t" region="region.after" style="defaultStyle" xml:id="subtitle245">10 a.m., water aerobics,<br/>2 p.m., line dancing, so on and so forth.</p>
<p begin="10022097501t" end="10075905005t" region="region.after" style="defaultStyle" xml:id="subtitle246">They always leave 3 p.m. to 4 p.m. free.<br/>Why? <span style="defaultStyle_2">Murder, She Wrote.</span></p>
<p begin="10077575006t" end="10100507500t" region="region.after" style="defaultStyle" xml:id="subtitle247">It's been in syndication<br/>since like the 1850s.</p>
<p begin="10102177501t" end="10122197501t" region="region.after" style="defaultStyle" xml:id="subtitle248">Let me tell you,<br/>when that thing comes on...</p>
<p begin="10123867502t" end="10148062507t" region="region.after" style="defaultStyle" xml:id="subtitle249">...it draws blue-hairs<br/>like moths to a bug zapper.</p>
<p begin="10149732508t" end="10188937508t" region="region.after" style="defaultStyle" xml:id="subtitle250">3:14 p.m.,<br/>end of the first act cliffhanger...</p>
<p begin="10190597500t" end="10216045005t" region="region.after" style="defaultStyle" xml:id="subtitle251">...first commercial up: Davis &amp; Main.</p>
<p begin="10217715006t" end="10256920006t" region="region.after" style="defaultStyle" xml:id="subtitle252">Guaranteed eyeballs, lots of them. There's<br/>nothing Sandpiper can do about that.</p>
<p begin="10258590007t" end="10296960006t" region="region.after" style="defaultStyle" xml:id="subtitle253">We ran a commercial a few years back,<br/>another class-action case...</p>
<p begin="10298630007t" end="10320310000t" region="region.after" style="defaultStyle" xml:id="subtitle254">...kind of a new thing for us.</p>
<p begin="10321980001t" end="10356185005t" region="region.after" style="defaultStyle" xml:id="subtitle255">It's not exactly my go-to, but,<br/>generally speaking, I'm open to it.</p>
<p begin="10357855006t" end="10394137502t" region="region.after" style="defaultStyle" xml:id="subtitle256">-We will talk next week.<br/>-Great.</p>
<p begin="10395807505t" end="10414157502t" region="region.after" style="defaultStyle" xml:id="subtitle257">Safe travels.</p>
<p begin="10626037505t" end="10662737501t" region="region.after" style="defaultStyle" xml:id="subtitle258"><span style="defaultStyle_2">If you or a family member have been</span><br/><span style="defaultStyle_2">diagnosed with mesothelioma...</span></p>
<p begin="10664407502t" end="10705700003t" region="region.after" style="defaultStyle" xml:id="subtitle259"><span style="defaultStyle_2">...or related conditions, you may be</span><br/><span style="defaultStyle_2">entitled to monetary damages.</span></p>
<p begin="10707370006t" end="10737400006t" region="region.after" style="defaultStyle" xml:id="subtitle260"><span style="defaultStyle_2">Mesothelioma is a rare lung disease</span><br/><span style="defaultStyle_2">usually associated...</span></p>
<p begin="10739070007t" end="10768682507t" region="region.after" style="defaultStyle" xml:id="subtitle261"><span style="defaultStyle_2">...with exposure to asbestos,</span><br/><span style="defaultStyle_2">a known human carcinogen.</span></p>
<p begin="10770352508t" end="10816227505t" region="region.after" style="defaultStyle" xml:id="subtitle262"><span style="defaultStyle_2">Long-term inhalation of asbestos fibers</span><br/><span style="defaultStyle_2">can cause serious or fatal illnesses...</span></p>
<p begin="10817897506t" end="10852092500t" region="region.after" style="defaultStyle" xml:id="subtitle263"><span style="defaultStyle_2">...including malignant lung cancer,</span><br/><span style="defaultStyle_2">Mesothelioma and asbestosis.</span></p>
<p begin="10853762502t" end="10887550006t" region="region.after" style="defaultStyle" xml:id="subtitle264">Remember, they worked real hard<br/>to get that just right.</p>
<p begin="10889220007t" end="10905900003t" region="region.after" style="defaultStyle" xml:id="subtitle265">To get what just right?</p>
<p begin="10907570006t" end="10930095008t" region="region.after" style="defaultStyle" xml:id="subtitle266">The swirl.</p>
<p begin="10938435006t" end="10968882507t" region="region.after" style="defaultStyle" xml:id="subtitle267">They wanted it kind of nebulous,<br/>but not too nebulous.</p>
<p begin="10970552508t" end="10991397500t" region="region.after" style="defaultStyle" xml:id="subtitle268">Then there was the issue of the speed.</p>
<p begin="10993067501t" end="11021845000t" region="region.after" style="defaultStyle" xml:id="subtitle269">I remember there were a lot<br/>of meetings about that.</p>
<p begin="11026855005t" end="11037282506t" region="region.after" style="defaultStyle" xml:id="subtitle270">I'll bet.</p>
<p begin="11038952507t" end="11082740001t" region="region.after" style="defaultStyle" xml:id="subtitle271"><span style="defaultStyle_2">For your free consultation</span><br/><span style="defaultStyle_2">call Davis &amp; Main at 505-242-7700.</span></p>
<p begin="11084410002t" end="11125702503t" region="region.after" style="defaultStyle" xml:id="subtitle272"><span style="defaultStyle_2">That's 505-242-7700</span></p>
<p begin="11162402500t" end="11207870006t" region="region.after" style="defaultStyle" xml:id="subtitle273">-Cliff signed off on this?<br/>-The partners were very happy.</p>
<p begin="11217462506t" end="11232472500t" region="region.after" style="defaultStyle" xml:id="subtitle274">What do you think?</p>
<p begin="11234142502t" end="11248327506t" region="region.after" style="defaultStyle" xml:id="subtitle275">I think:</p>
<p begin="11249997508t" end="11280027508t" region="region.after" style="defaultStyle" xml:id="subtitle276">What ever happened to showmanship?</p>
<p begin="11322980001t" end="11364690002t" region="region.after" style="defaultStyle" xml:id="subtitle277">Yo, check it out. Ricola!</p>
<p begin="11366360003t" end="11390137508t" region="region.after" style="defaultStyle" xml:id="subtitle278">-Ricola!<br/>-Hey.</p>
<p begin="11391797500t" end="11421410000t" region="region.after" style="defaultStyle" xml:id="subtitle279">Why don't you two ass-clowns act<br/>like the professionals...</p>
<p begin="11423080001t" end="11440605008t" region="region.after" style="defaultStyle" xml:id="subtitle280">...your parents are paying<br/>for you to become?</p>
<p begin="11442265000t" end="11491897500t" region="region.after" style="defaultStyle" xml:id="subtitle281">-This happens to be very valuable.<br/>-Yeah? What is it?</p>
<p begin="11493985001t" end="11531937500t" region="region.after" style="defaultStyle" xml:id="subtitle282">This one is the Alpine shepherd boy.<br/>It's for her nephew.</p>
<p begin="11533607501t" end="11569900007t" region="region.after" style="defaultStyle" xml:id="subtitle283">So come, join me.<br/>Production meeting, bring it in.</p>
<p begin="11571560000t" end="11611192508t" region="region.after" style="defaultStyle" xml:id="subtitle284">All right, now look,<br/>teamwork makes the dream work.</p>
<p begin="11612852500t" end="11649562507t" region="region.after" style="defaultStyle" xml:id="subtitle285">Together we can make something,<br/>dare I say it, bravura.</p>
<p begin="11651232508t" end="11674582502t" region="region.after" style="defaultStyle" xml:id="subtitle286">This is a golden opportunity,<br/>especially for you.</p>
<p begin="11676252503t" end="11710457508t" region="region.after" style="defaultStyle" xml:id="subtitle287">This will play all around the Southwest,<br/>so who knows what it can lead to?</p>
<p begin="11712117500t" end="11729642507t" region="region.after" style="defaultStyle" xml:id="subtitle288">Better lead to a hundred bucks each.</p>
<p begin="11731312508t" end="11758837506t" region="region.after" style="defaultStyle" xml:id="subtitle289">-What is it with you and money?<br/>-Saving up for a VX2000.</p>
<p begin="11760507508t" end="11801382508t" region="region.after" style="defaultStyle" xml:id="subtitle290">Hey, pop quiz. What do we three have<br/>in common with the greats?</p>
<p begin="11803042500t" end="11833907501t" region="region.after" style="defaultStyle" xml:id="subtitle291">Welles, Fellini, Bergman, the biggies.</p>
<p begin="11835577502t" end="11847675005t" region="region.after" style="defaultStyle" xml:id="subtitle292">What?</p>
<p begin="11849345006t" end="11863937501t" region="region.after" style="defaultStyle" xml:id="subtitle293">All three of them, to a man...</p>
<p begin="11865607502t" end="11907735005t" region="region.after" style="defaultStyle" xml:id="subtitle294">...worked in the highly lucrative,<br/>creatively-rewarding field of advertising.</p>
<p begin="11909405006t" end="11955697502t" region="region.after" style="defaultStyle" xml:id="subtitle295">And tonight we join them.<br/>This is heady stuff, right?</p>
<p begin="11957367505t" end="11979892507t" region="region.after" style="defaultStyle" xml:id="subtitle296">Okay, so pay attention.</p>
<p begin="11981562508t" end="12016175003t" region="region.after" style="defaultStyle" xml:id="subtitle297">We open on granny<br/>and she is rocking.</p>
<p begin="12017845005t" end="12080410007t" region="region.after" style="defaultStyle" xml:id="subtitle298">So, she's back and forth, just very--<br/>Back and forth.</p>
<p begin="12082070000t" end="12121702508t" region="region.after" style="defaultStyle" xml:id="subtitle299">And then, very slowly and smoothly...</p>
<p begin="12123362500t" end="12164655001t" region="region.after" style="defaultStyle" xml:id="subtitle300">...the camera moves towards--</p>
<p begin="12166325003t" end="12188015005t" region="region.after" style="defaultStyle" xml:id="subtitle301">-Dolly.<br/>-A dolly, good.</p>
<p begin="12189685006t" end="12202190000t" region="region.after" style="defaultStyle" xml:id="subtitle302">See a dolly here?</p>
<p begin="12210122507t" end="12239317506t" region="region.after" style="defaultStyle" xml:id="subtitle303">-You guys didn't bring a dolly?<br/>-Nope, no dolly.</p>
<p begin="12240987508t" end="12266842503t" region="region.after" style="defaultStyle" xml:id="subtitle304">-You didn't ask for a dolly.<br/>-Gotta ask. Dolly is extra.</p>
<p begin="12268512506t" end="12300212507t" region="region.after" style="defaultStyle" xml:id="subtitle305">-That's true.<br/>-Okay, no dolly.</p>
<p begin="12320232507t" end="12340252507t" region="region.after" style="defaultStyle" xml:id="subtitle306">We will improvise, then.</p>
<p begin="12341922508t" end="12382370000t" region="region.after" style="defaultStyle" xml:id="subtitle307">Stay with me.<br/>She's rocking. She's shivering.</p>
<p begin="12409905006t" end="12430760007t" region="region.after" style="defaultStyle" xml:id="subtitle308">She's clutching...</p>
<p begin="12432420000t" end="12454945001t" region="region.after" style="defaultStyle" xml:id="subtitle309">...at a tattered shawl.</p>
<p begin="12468712506t" end="12508335005t" region="region.after" style="defaultStyle" xml:id="subtitle310">They turned the heat off on her,<br/>these evil bastards.</p>
<p begin="12510005006t" end="12532112508t" region="region.after" style="defaultStyle" xml:id="subtitle311">She's cold and hungry,<br/>she's friendless.</p>
<p begin="12533772500t" end="12575065001t" region="region.after" style="defaultStyle" xml:id="subtitle312">This is heart-rending stuff, man.</p>
<p begin="12587997505t" end="12624697501t" region="region.after" style="defaultStyle" xml:id="subtitle313">Okay, it's a oner<br/>and it's shot in glorious black and white.</p>
<p begin="12626367502t" end="12650562507t" region="region.after" style="defaultStyle" xml:id="subtitle314">-We can do that, right?<br/>-Yeah.</p>
<p begin="12668912506t" end="12709370006t" region="region.after" style="defaultStyle" xml:id="subtitle315">So, that's it, old lady in a chair?<br/>That's your commercial?</p>
<p begin="12726050002t" end="12746487502t" region="region.after" style="defaultStyle" xml:id="subtitle316">Does anybody like you?</p>
<p begin="12767342503t" end="12796120002t" region="region.after" style="defaultStyle" xml:id="subtitle317">I'm ready for my close-up, Mr. McGill.</p>
<p begin="13279105005t" end="13298707505t" region="region.after" style="defaultStyle" xml:id="subtitle318"><span style="defaultStyle_2">He makes the grab, two outs here.</span></p>
<p begin="13300377506t" end="13330825006t" region="region.after" style="defaultStyle" xml:id="subtitle319"><span style="defaultStyle_2">He got underneath that one.</span><br/><span style="defaultStyle_2">I think he's....</span></p>
<p begin="13332495008t" end="13356262502t" region="region.after" style="defaultStyle" xml:id="subtitle320"><span style="defaultStyle_2">An easy, easy pop fly</span><br/><span style="defaultStyle_2">out to dead center.</span></p>
<p begin="13357932503t" end="13372952508t" region="region.after" style="defaultStyle" xml:id="subtitle321"><span style="defaultStyle_2">That brings up....</span></p>
<p begin="13380457506t" end="13417157502t" region="region.after" style="defaultStyle" xml:id="subtitle322"><span style="defaultStyle_2">Murphy's gone 13 for 29</span><br/><span style="defaultStyle_2">over his last eight games...</span></p>
<p begin="13418827505t" end="13443847500t" region="region.after" style="defaultStyle" xml:id="subtitle323"><span style="defaultStyle_2">...batting a blistering .343.</span></p>
<p begin="13452615008t" end="13476800002t" region="region.after" style="defaultStyle" xml:id="subtitle324"><span style="defaultStyle_2">And now Louis again</span><br/><span style="defaultStyle_2">working quickly with the bench.</span></p>
<p begin="13478470003t" end="13513499999t" region="region.after" style="defaultStyle" xml:id="subtitle325"><span style="defaultStyle_2">Murphy swings, it's a two-hopper</span><br/><span style="defaultStyle_2">into the crowd, foul ball.</span></p>
<p begin="14503665008t" end="14519927505t" region="region.after" style="defaultStyle" xml:id="subtitle326">Have a good one.</p>
<p begin="14800625005t" end="14825227500t" region="region.after" style="defaultStyle" xml:id="subtitle327">Hey, honey, what's happening?</p>
<p begin="14826897501t" end="14844422508t" region="region.after" style="defaultStyle" xml:id="subtitle328">What's wrong?</p>
<p begin="14850675005t" end="14869442503t" region="region.after" style="defaultStyle" xml:id="subtitle329">What happened?</p>
<p begin="15010417505t" end="15025845000t" region="region.after" style="defaultStyle" xml:id="subtitle330">-Where's Kaylee?<br/>-She's at school.</p>
<p begin="15027515001t" end="15058797502t" region="region.after" style="defaultStyle" xml:id="subtitle331">-She's fine, she doesn't know about it.<br/>-Are you all right?</p>
<p begin="15061720006t" end="15079652503t" region="region.after" style="defaultStyle" xml:id="subtitle332">Let me show you.</p>
<p begin="15100925005t" end="15125945000t" region="region.after" style="defaultStyle" xml:id="subtitle333">It's up there.</p>
<p begin="15127615001t" end="15143887508t" region="region.after" style="defaultStyle" xml:id="subtitle334">You see it?</p>
<p begin="15145547500t" end="15163490007t" region="region.after" style="defaultStyle" xml:id="subtitle335">It's right up there.</p>
<p begin="15174752508t" end="15199355003t" region="region.after" style="defaultStyle" xml:id="subtitle336">You see that?<br/>You see the shape of it?</p>
<p begin="15212287506t" end="15243152507t" region="region.after" style="defaultStyle" xml:id="subtitle337">-You do see it, right?<br/>-Uh, I see it.</p>
<p begin="15260250003t" end="15275677500t" region="region.after" style="defaultStyle" xml:id="subtitle338">What time did you hear the shots?</p>
<p begin="15277347501t" end="15303212507t" region="region.after" style="defaultStyle" xml:id="subtitle339">At 2:13 this morning.<br/>I looked at the clock.</p>
<p begin="15304882508t" end="15333660007t" region="region.after" style="defaultStyle" xml:id="subtitle340">It was three of them.<br/>It was exactly like last time.</p>
<p begin="15335319999t" end="15350340003t" region="region.after" style="defaultStyle" xml:id="subtitle341">And you didn't call the police?</p>
<p begin="15352010006t" end="15378282502t" region="region.after" style="defaultStyle" xml:id="subtitle342">No, I.... What's the point?</p>
<p begin="15420827505t" end="15447100001t" region="region.after" style="defaultStyle" xml:id="subtitle343">I'm thinking outside the box, but....</p>
<p begin="15458362502t" end="15485469999t" region="region.after" style="defaultStyle" xml:id="subtitle344">You think maybe it's possible<br/>that you dreamed it?</p>
<p begin="15487140001t" end="15497985001t" region="region.after" style="defaultStyle" xml:id="subtitle345">It happens sometimes.</p>
<p begin="15499655003t" end="15518422502t" region="region.after" style="defaultStyle" xml:id="subtitle346">I didn't dream it, Mike.</p>
<p begin="15520092503t" end="15545529999t" region="region.after" style="defaultStyle" xml:id="subtitle347">Because I didn't sleep a wink last night.</p>
<p begin="15547200001t" end="15573482507t" region="region.after" style="defaultStyle" xml:id="subtitle348">That came from a bullet.<br/>I mean, it must have.</p>
<p begin="15575152508t" end="15597667501t" region="region.after" style="defaultStyle" xml:id="subtitle349">It wasn't there before last night.<br/>I promise you.</p>
<p begin="15599337502t" end="15621862506t" region="region.after" style="defaultStyle" xml:id="subtitle350">-And I don't know--<br/>-Okay.</p>
<p begin="15623950007t" end="15639377502t" region="region.after" style="defaultStyle" xml:id="subtitle351">Okay.</p>
<p begin="15641047505t" end="15659815003t" region="region.after" style="defaultStyle" xml:id="subtitle352">Jesus.</p>
<p begin="15666485000t" end="15691515005t" region="region.after" style="defaultStyle" xml:id="subtitle353">I mean, I was here.<br/>I was here and you weren't.</p>
<p begin="15693185006t" end="15715292508t" region="region.after" style="defaultStyle" xml:id="subtitle354">I believe you.</p>
<p begin="15733225006t" end="15754080007t" region="region.after" style="defaultStyle" xml:id="subtitle355">I believe you.</p>
<p begin="15794120007t" end="15810382503t" region="region.after" style="defaultStyle" xml:id="subtitle356">All right.</p>
<p begin="15817887501t" end="15852927506t" region="region.after" style="defaultStyle" xml:id="subtitle357">That's it. We're getting you<br/>and Kaylee out of this house.</p>
<p begin="15856675000t" end="15877947501t" region="region.after" style="defaultStyle" xml:id="subtitle358">End of story.</p>
<p begin="16094002507t" end="16125702508t" region="region.after" style="defaultStyle" xml:id="subtitle359">-Do you ever wonder about these things?<br/>-What things?</p>
<p begin="16128615001t" end="16151140003t" region="region.after" style="defaultStyle" xml:id="subtitle360">This. Like what's the story with these?</p>
<p begin="16159897502t" end="16203695006t" region="region.after" style="defaultStyle" xml:id="subtitle361">Who was it who first said,<br/>"Hey, I know: big bowl of balls."</p>
<p begin="16205365008t" end="16224132507t" region="region.after" style="defaultStyle" xml:id="subtitle362">I don't know. They came with the place.</p>
<p begin="16225802508t" end="16265842508t" region="region.after" style="defaultStyle" xml:id="subtitle363">No shit. They're in<br/>every corporate apartment in the world.</p>
<p begin="16267502500t" end="16281687505t" region="region.after" style="defaultStyle" xml:id="subtitle364">They're like the Gideon Bible.</p>
<p begin="16283357506t" end="16321727505t" region="region.after" style="defaultStyle" xml:id="subtitle365">Hey. Don't be jealous of my<br/>big bowl of balls. It's unbecoming.</p>
<p begin="16323397506t" end="16348000001t" region="region.after" style="defaultStyle" xml:id="subtitle366">Why do they all have<br/>to have empty vases?</p>
<p begin="16349670002t" end="16388040001t" region="region.after" style="defaultStyle" xml:id="subtitle367">Well, it's the law. Plus it's a metaphor.</p>
<p begin="16398885001t" end="16425167508t" region="region.after" style="defaultStyle" xml:id="subtitle368">Gotta say, I will miss<br/>the nail salon's vibrating chairs.</p>
<p begin="16431837505t" end="16461032503t" region="region.after" style="defaultStyle" xml:id="subtitle369">Well, for you, I can make<br/>any chair in this place vibrate.</p>
<p begin="16467702500t" end="16486062508t" region="region.after" style="defaultStyle" xml:id="subtitle370">You ready for this?</p>
<p begin="16500655003t" end="16508995001t" region="region.after" style="defaultStyle" xml:id="subtitle371">Okay.</p>
<p begin="16510665003t" end="16520675003t" region="region.after" style="defaultStyle" xml:id="subtitle372">Here goes.</p>
<p begin="16522345005t" end="16556957500t" region="region.after" style="defaultStyle" xml:id="subtitle373">You're 86 years old, you're a resident<br/>of Sandpiper, Colorado Springs.</p>
<p begin="16558627501t" end="16586162508t" region="region.after" style="defaultStyle" xml:id="subtitle374">You just finished your afternoon snack,<br/>lime Jell-O.</p>
<p begin="16588240001t" end="16608677501t" region="region.after" style="defaultStyle" xml:id="subtitle375">-Lime. Got it.<br/>-You're in the day room.</p>
<p begin="16610347502t" end="16630367502t" region="region.after" style="defaultStyle" xml:id="subtitle376">You're watching<br/>your favorite TV program.</p>
<p begin="16632037505t" end="16659980002t" region="region.after" style="defaultStyle" xml:id="subtitle377">What's this? There's been another<br/>murder in Cabot Cove?</p>
<p begin="16661650003t" end="16672912506t" region="region.after" style="defaultStyle" xml:id="subtitle378">-No.<br/>-Yes.</p>
<p begin="16674582507t" end="16689592502t" region="region.after" style="defaultStyle" xml:id="subtitle379">The sheriff is in over his head.</p>
<p begin="16691262503t" end="16723380006t" region="region.after" style="defaultStyle" xml:id="subtitle380">Jessica Fletcher has to put aside<br/>the novel she's been writing...</p>
<p begin="16725050007t" end="16743817506t" region="region.after" style="defaultStyle" xml:id="subtitle381">...and assist law enforcement.</p>
<p begin="16745487508t" end="16770090002t" region="region.after" style="defaultStyle" xml:id="subtitle382">Shocker,<br/>the killer left behind a cryptogram...</p>
<p begin="16771760003t" end="16798450001t" region="region.after" style="defaultStyle" xml:id="subtitle383">...and commercial.</p>
<p begin="16888122500t" end="16926085008t" region="region.after" style="defaultStyle" xml:id="subtitle384"><span style="defaultStyle_2">My husband and I scrimped and saved</span><br/><span style="defaultStyle_2">for so many years.</span></p>
<p begin="16927745000t" end="16946522508t" region="region.after" style="defaultStyle" xml:id="subtitle385"><span style="defaultStyle_2">We did our best</span><br/><span style="defaultStyle_2">to build a nest egg...</span></p>
<p begin="16948182500t" end="16977795000t" region="region.after" style="defaultStyle" xml:id="subtitle386"><span style="defaultStyle_2">...so that we wouldn't be a burden</span><br/><span style="defaultStyle_2">to our family.</span></p>
<p begin="16979465001t" end="17016175008t" region="region.after" style="defaultStyle" xml:id="subtitle387"><span style="defaultStyle_2">After Ronald passed,</span><br/><span style="defaultStyle_2">I moved to an assisted living facility.</span></p>
<p begin="17017835000t" end="17057039999t" region="region.after" style="defaultStyle" xml:id="subtitle388"><span style="defaultStyle_2">A nice place. They told me</span><br/><span style="defaultStyle_2">they'd take care of everything.</span></p>
<p begin="17058710001t" end="17097497500t" region="region.after" style="defaultStyle" xml:id="subtitle389"><span style="defaultStyle_2">But, then one day,</span><br/><span style="defaultStyle_2">they said all my money was gone.</span></p>
<p begin="17099167501t" end="17120857502t" region="region.after" style="defaultStyle" xml:id="subtitle390"><span style="defaultStyle_2">How could that be?</span></p>
<p begin="17122527505t" end="17143800006t" region="region.after" style="defaultStyle" xml:id="subtitle391"><span style="defaultStyle_2">Where did it all go?</span></p>
<p begin="17152975005t" end="17178412500t" region="region.after" style="defaultStyle" xml:id="subtitle392">-That's not a real tear?<br/>-<span style="defaultStyle_2">If you or a loved one is a resident...</span></p>
<p begin="17179247501t" end="17200102502t" region="region.after" style="defaultStyle" xml:id="subtitle393">-Visine.<br/><span style="defaultStyle_2">-...of a Sandpiper Crossing facility...</span></p>
<p begin="17201772503t" end="17226802508t" region="region.after" style="defaultStyle" xml:id="subtitle394"><span style="defaultStyle_2">...or other</span><br/><span style="defaultStyle_2">associated retirement community...</span></p>
<p begin="17228462500t" end="17250152502t" region="region.after" style="defaultStyle" xml:id="subtitle395"><span style="defaultStyle_2">...you may be eligible</span><br/><span style="defaultStyle_2">to receive compensation.</span></p>
<p begin="17251822503t" end="17294367506t" region="region.after" style="defaultStyle" xml:id="subtitle396"><span style="defaultStyle_2">For a free consultation,</span><br/><span style="defaultStyle_2">call the law offices of Davis &amp; Main...</span></p>
<p begin="17296037508t" end="17321475003t" region="region.after" style="defaultStyle" xml:id="subtitle397"><span style="defaultStyle_2">...at 505-242-7700.</span></p>
<p begin="17323145005t" end="17362767505t" region="region.after" style="defaultStyle" xml:id="subtitle398"><span style="defaultStyle_2">That's 505-242-7700.</span></p>
<p begin="17399885001t" end="17416157508t" region="region.after" style="defaultStyle" xml:id="subtitle399">Well?</p>
<p begin="17424080006t" end="17455780007t" region="region.after" style="defaultStyle" xml:id="subtitle400">You made that,<br/>with some film students?</p>
<p begin="17457440000t" end="17472460003t" region="region.after" style="defaultStyle" xml:id="subtitle401">I directed.</p>
<p begin="17474130006t" end="17510412502t" region="region.after" style="defaultStyle" xml:id="subtitle402">It looks professional.</p>
<p begin="17520840002t" end="17545870007t" region="region.after" style="defaultStyle" xml:id="subtitle403">-And?<br/>-And if I were an 86-year-old...</p>
<p begin="17547530000t" end="17572977505t" region="region.after" style="defaultStyle" xml:id="subtitle404">...Sandpiper resident...</p>
<p begin="17574647506t" end="17598832500t" region="region.after" style="defaultStyle" xml:id="subtitle405">-...I'd be dialing.<br/>-Yes.</p>
<p begin="17600502502t" end="17612182503t" region="region.after" style="defaultStyle" xml:id="subtitle406">Up top.</p>
<p begin="17613852506t" end="17642212503t" region="region.after" style="defaultStyle" xml:id="subtitle407">And all made in accordance<br/>with the rules and regulations...</p>
<p begin="17643882506t" end="17669737501t" region="region.after" style="defaultStyle" xml:id="subtitle408">...of the American Bar Association.</p>
<p begin="17671407502t" end="17686427508t" region="region.after" style="defaultStyle" xml:id="subtitle409">Good.</p>
<p begin="17727302508t" end="17757740000t" region="region.after" style="defaultStyle" xml:id="subtitle410">I can't believe<br/>Davis &amp; Main went for it.</p>
<p begin="17759410001t" end="17772760003t" region="region.after" style="defaultStyle" xml:id="subtitle411">Well...</p>
<p begin="17780682502t" end="17810295001t" region="region.after" style="defaultStyle" xml:id="subtitle412">-...I'm in charge of the department.<br/>-Yeah, but still, you know.</p>
<p begin="17811965003t" end="17836577508t" region="region.after" style="defaultStyle" xml:id="subtitle413">Cliff Main was fine with this.</p>
<p begin="17839907501t" end="17852422503t" region="region.after" style="defaultStyle" xml:id="subtitle414">Why wouldn't he be?</p>
<p begin="17854092506t" end="17872025003t" region="region.after" style="defaultStyle" xml:id="subtitle415">He.... No, it's....</p>
<p begin="17873695005t" end="17893715005t" region="region.after" style="defaultStyle" xml:id="subtitle416">It's fantastic.</p>
<p begin="17895385006t" end="17920405001t" region="region.after" style="defaultStyle" xml:id="subtitle417">Let's celebrate. I'm getting more wine.<br/>You want some?</p>
<p begin="17922075003t" end="17941260002t" region="region.after" style="defaultStyle" xml:id="subtitle418">Absolutely.</p>
<p begin="18372525003t" end="18400885001t" region="region.after" style="defaultStyle" xml:id="subtitle419">Thursday at 11<br/>in the Conference Room?</p>
<p begin="18589405000t" end="18611930002t" region="region.after" style="defaultStyle" xml:id="subtitle420">Very good. Thank you.</p>
<p begin="18692427502t" end="18715787506t" region="region.after" style="defaultStyle" xml:id="subtitle421">Colorado Springs, Colorado. Yeah.</p>
<p begin="18717457508t" end="18759157500t" region="region.after" style="defaultStyle" xml:id="subtitle422">I'd like the number<br/>for KKTV channel 11.</p>
<p begin="18768342508t" end="18810042500t" region="region.after" style="defaultStyle" xml:id="subtitle423">Omar! What's the cut-off for FedEx?<br/>Need to get a package out, <span style="defaultStyle_2">tout de suite.</span></p>
<p begin="18825062506t" end="18858432508t" region="region.after" style="defaultStyle" xml:id="subtitle424">Yes, can you connect me<br/>to your ad sales department?</p>
<p begin="18860092500t" end="18877200007t" region="region.after" style="defaultStyle" xml:id="subtitle425">Thanks.</p>
<p begin="18878860000t" end="18904725005t" region="region.after" style="defaultStyle" xml:id="subtitle426">Gums look good. No recession.</p>
<p begin="18906395006t" end="18935172506t" region="region.after" style="defaultStyle" xml:id="subtitle427">Tongue looks good too.<br/>Eyes are clear.</p>
<p begin="18936842507t" end="18957280007t" region="region.after" style="defaultStyle" xml:id="subtitle428">This little lady's in fine fettle.</p>
<p begin="18958940000t" end="18992727502t" region="region.after" style="defaultStyle" xml:id="subtitle429">-Can have one of the girls trim her nails.<br/>-No, some other time.</p>
<p begin="19016087506t" end="19030262500t" region="region.after" style="defaultStyle" xml:id="subtitle430">What do you got for me?</p>
<p begin="19043195003t" end="19063632503t" region="region.after" style="defaultStyle" xml:id="subtitle431">Bodyguard job, 200 bucks.</p>
<p begin="19066137506t" end="19086992507t" region="region.after" style="defaultStyle" xml:id="subtitle432">What else?</p>
<p begin="19088662508t" end="19117857508t" region="region.after" style="defaultStyle" xml:id="subtitle433">For you,<br/>that's the best fit I've got.</p>
<p begin="19157897508t" end="19177082507t" region="region.after" style="defaultStyle" xml:id="subtitle434">I know a loan shark.</p>
<p begin="19178752508t" end="19203772503t" region="region.after" style="defaultStyle" xml:id="subtitle435">Always needs<br/>enforcement and recovery.</p>
<p begin="19205442506t" end="19230462500t" region="region.after" style="defaultStyle" xml:id="subtitle436">Pays good and it's steady work.</p>
<p begin="19232132502t" end="19254657505t" region="region.after" style="defaultStyle" xml:id="subtitle437">Most of the time<br/>we're just talking intimidation.</p>
<p begin="19256327506t" end="19292192502t" region="region.after" style="defaultStyle" xml:id="subtitle438">-Strictly verbal.<br/>-Most of the time.</p>
<p begin="19294697505t" end="19321387501t" region="region.after" style="defaultStyle" xml:id="subtitle439">I'm not breaking legs. What else?</p>
<p begin="19338495008t" end="19353922503t" region="region.after" style="defaultStyle" xml:id="subtitle440">Look.</p>
<p begin="19356427506t" end="19374777505t" region="region.after" style="defaultStyle" xml:id="subtitle441">We discussed this.</p>
<p begin="19376447506t" end="19404807505t" region="region.after" style="defaultStyle" xml:id="subtitle442">You want next-level pay,<br/>you gotta do next-level work.</p>
<p begin="19406477506t" end="19427332507t" region="region.after" style="defaultStyle" xml:id="subtitle443">I respect where you're coming from.</p>
<p begin="19429002508t" end="19460275000t" region="region.after" style="defaultStyle" xml:id="subtitle444">I do. But that's just how it goes.</p>
<p begin="19513247502t" end="19526180006t" region="region.after" style="defaultStyle" xml:id="subtitle445">All right.</p>
<p begin="19527850007t" end="19552870002t" region="region.after" style="defaultStyle" xml:id="subtitle446">She's gonna need a DHPP shot.</p>
<p begin="19554540003t" end="19584570003t" region="region.after" style="defaultStyle" xml:id="subtitle447">Six months.<br/>We'll send you a reminder card.</p>
<p begin="19586240006t" end="19603755003t" region="region.after" style="defaultStyle" xml:id="subtitle448">Till then.</p>
<p begin="19613347502t" end="19627115006t" region="region.after" style="defaultStyle" xml:id="subtitle449">Give me the bodyguard job.</p>
<p begin="19649630000t" end="19660057500t" region="region.after" style="defaultStyle" xml:id="subtitle450">For 200?</p>
<p begin="19693010002t" end="19716370006t" region="region.after" style="defaultStyle" xml:id="subtitle451">Call you with the where and the when.</p>
<p begin="20039195008t" end="20059632508t" region="region.after" style="defaultStyle" xml:id="subtitle452">Yes, sir. He's expecting your call.</p>
<p begin="20085070003t" end="20107595006t" region="region.after" style="defaultStyle" xml:id="subtitle453">-So, everybody knows--<br/>-They know.</p>
<p begin="20109265008t" end="20142625001t" region="region.after" style="defaultStyle" xml:id="subtitle454">Every line starting with 7700<br/>has been rerouted to the bullpen.</p>
<p begin="20144295003t" end="20170150000t" region="region.after" style="defaultStyle" xml:id="subtitle455">Plus your office.<br/>The assistants know to keep them open.</p>
<p begin="20171820001t" end="20196850006t" region="region.after" style="defaultStyle" xml:id="subtitle456">So, if you're on a call<br/>and another call comes in...</p>
<p begin="20198937508t" end="20217287506t" region="region.after" style="defaultStyle" xml:id="subtitle457">...it doesn't go to<br/>an answering machine?</p>
<p begin="20218957508t" end="20244812503t" region="region.after" style="defaultStyle" xml:id="subtitle458">Very important. Old people<br/>don't like talking to robots.</p>
<p begin="20246482506t" end="20282765001t" region="region.after" style="defaultStyle" xml:id="subtitle459">If I'm on a call and another call<br/>comes in, it'll roll over to Maida.</p>
<p begin="20284435003t" end="20306960006t" region="region.after" style="defaultStyle" xml:id="subtitle460">After that, Iris will get the next one.</p>
<p begin="20308630007t" end="20334485003t" region="region.after" style="defaultStyle" xml:id="subtitle461">Then Julian and then Barbara<br/>and Yvonne...</p>
<p begin="20336155005t" end="20354087502t" region="region.after" style="defaultStyle" xml:id="subtitle462">...right on down the line.</p>
<p begin="20355757505t" end="20390787500t" region="region.after" style="defaultStyle" xml:id="subtitle463">Good. Let's make that the plan then.</p>
<p begin="20395380003t" end="20413730002t" region="region.after" style="defaultStyle" xml:id="subtitle464">Oh, so....</p>
<p begin="20422070001t" end="20437925006t" region="region.after" style="defaultStyle" xml:id="subtitle465">What time do you have?</p>
<p begin="20439595008t" end="20476295005t" region="region.after" style="defaultStyle" xml:id="subtitle466">Quarter after.<br/>It should be running now, right?</p>
<p begin="20502150001t" end="20525510003t" region="region.after" style="defaultStyle" xml:id="subtitle467">Is there anything else?</p>
<p begin="20533015001t" end="20555957505t" region="region.after" style="defaultStyle" xml:id="subtitle468">No. Thanks. It's--</p>
<p begin="20557627506t" end="20588492507t" region="region.after" style="defaultStyle" xml:id="subtitle469">I'll just be in my office.</p>
<p begin="20805372503t" end="20822887501t" region="region.after" style="defaultStyle" xml:id="subtitle470">Come on.</p>
<p begin="20836237505t" end="20871267500t" region="region.after" style="defaultStyle" xml:id="subtitle471">Come on, Colorado Springs, come on.</p>
<p begin="21077312506t" end="21111925000t" region="region.after" style="defaultStyle" xml:id="subtitle472">Good afternoon, Davis &amp; Main,<br/>attorneys at law, how may we help you?</p>
<p begin="21118187506t" end="21146130003t" region="region.after" style="defaultStyle" xml:id="subtitle473">Yes, ma'am.<br/>Yes, ma'am, that is unfortunate.</p>
<p begin="21147800006t" end="21162810001t" region="region.after" style="defaultStyle" xml:id="subtitle474">Now, to get your case started...</p>
<p begin="21164480002t" end="21196597505t" region="region.after" style="defaultStyle" xml:id="subtitle475">...may I ask for a name and a number<br/>for one of our attorneys to reach you?</p>
<p begin="21198267506t" end="21234132502t" region="region.after" style="defaultStyle" xml:id="subtitle476">Good afternoon, Davis &amp; Main, attorneys<br/>at law. How can I help you? Yes, that is--</p>
<p begin="21236220003t" end="21252065000t" region="region.after" style="defaultStyle" xml:id="subtitle477">Good afternoon, Davis &amp; Main.</p>
<p begin="21314630002t" end="21348417506t" region="region.after" style="defaultStyle" xml:id="subtitle478">Good afternoon, Davis &amp; Main.<br/>Sandpiper hotline, how may we help you?</p>
<p begin="21369690007t" end="21384700002t" region="region.after" style="defaultStyle" xml:id="subtitle479">We'll get back to you.</p>
<p begin="21386370003t" end="21415982503t" region="region.after" style="defaultStyle" xml:id="subtitle480">Yes, ma'am. We'll be happy to send<br/>an information packet to you.</p>
<p begin="21417652506t" end="21431827500t" region="region.after" style="defaultStyle" xml:id="subtitle481">May I ask...</p>
<p begin="21433497501t" end="21469790007t" region="region.after" style="defaultStyle" xml:id="subtitle482">...are you currently a resident<br/>of a Sandpiper Crossing facility?</p>
<p begin="21484382502t" end="21502732500t" region="region.after" style="defaultStyle" xml:id="subtitle483">-Good afternoon, Davis &amp; Main.<br/>-Good afternoon, Davis &amp; Main.</p>
<p begin="21504820002t" end="21539442507t" region="region.after" style="defaultStyle" xml:id="subtitle484">-Bingo.<br/>-Are you currently a resident at....</p>
<p begin="21959027506t" end="21972367500t" region="region.after" style="defaultStyle" xml:id="subtitle485">Yeah.</p>
<p begin="21974037501t" end="22011990000t" region="region.after" style="defaultStyle" xml:id="subtitle486"><span style="defaultStyle_2">Something came in this evening,</span><br/><span style="defaultStyle_2">and it's definitely next-level pay.</span></p>
<p begin="22016165003t" end="22028680006t" region="region.after" style="defaultStyle" xml:id="subtitle487">Yeah?</p>
<p begin="22030350007t" end="22054117501t" region="region.after" style="defaultStyle" xml:id="subtitle488"><span style="defaultStyle_2">It's probably a long shot,</span><br/><span style="defaultStyle_2">given your selectivity.</span></p>
<p begin="22065797502t" end="22082895000t" region="region.after" style="defaultStyle" xml:id="subtitle489"><span style="defaultStyle_2">What's the job?</span></p>
<p begin="22084565001t" end="22104585001t" region="region.after" style="defaultStyle" xml:id="subtitle490">I asked. The guy wouldn't tell me.</p>
<p begin="22106255003t" end="22153800001t" region="region.after" style="defaultStyle" xml:id="subtitle491">But whatever it is, it's serious money.<br/>And the guy?</p>
<p begin="22165480002t" end="22194257501t" region="region.after" style="defaultStyle" xml:id="subtitle492">He specifically asked for you.</p>
<p begin="22202180000t" end="22225540002t" region="region.after" style="defaultStyle" xml:id="subtitle493">And who's the guy?</p>
<p begin="22231802508t" end="22254317501t" region="region.after" style="defaultStyle" xml:id="subtitle494"><span style="defaultStyle_2">-I can't hold it, sir.</span><br/><span style="defaultStyle_2">-No control in the planes.</span></p>
<p begin="22255987502t" end="22276842503t" region="region.after" style="defaultStyle" xml:id="subtitle495"><span style="defaultStyle_2">We're going down and fast.</span></p>
<p begin="22278512506t" end="22313542500t" region="region.after" style="defaultStyle" xml:id="subtitle496">"We're going down and fast."<br/>Check this out. This is the good part.</p>
<p begin="22315212502t" end="22347330003t" region="region.after" style="defaultStyle" xml:id="subtitle497"><span style="defaultStyle_2">-Anything?</span><br/>-So do they all die? Tell me that much.</p>
<p begin="22363175000t" end="22394040001t" region="region.after" style="defaultStyle" xml:id="subtitle498">Does Rock Hudson run them<br/>into an iceberg?</p>
<p begin="22410730007t" end="22444925001t" region="region.after" style="defaultStyle" xml:id="subtitle499">Is this before or after<br/>he did <span style="defaultStyle_2">McMillan &amp; Wife?</span></p>
<p begin="22446595003t" end="22473285000t" region="region.after" style="defaultStyle" xml:id="subtitle500">Shut up, watch the movie.</p>
<p begin="22500820007t" end="22528762506t" region="region.after" style="defaultStyle" xml:id="subtitle501">What is this weird fascination<br/>you have with stories...</p>
<p begin="22530432507t" end="22558375005t" region="region.after" style="defaultStyle" xml:id="subtitle502">...of men trapped on the North Pole?</p>
<p begin="22560045006t" end="22581317508t" region="region.after" style="defaultStyle" xml:id="subtitle503"><span style="defaultStyle_2">Ice Station Zebra</span> is on the North Pole.</p>
<p begin="22582977500t" end="22619270006t" region="region.after" style="defaultStyle" xml:id="subtitle504"><span style="defaultStyle_2">The Thing</span> takes place on the South Pole.<br/>They could not be any more different.</p>
<p begin="22620940007t" end="22636367502t" region="region.after" style="defaultStyle" xml:id="subtitle505"><span style="defaultStyle_2">-Aye, sir.</span><br/>-My dad loves this one.</p>
<p begin="22638037505t" end="22671825008t" region="region.after" style="defaultStyle" xml:id="subtitle506"><span style="defaultStyle_2">-Put it in the red.</span><br/>-Yeah. Him and Howard Hughes.</p>
<p begin="22673485000t" end="22691427508t" region="region.after" style="defaultStyle" xml:id="subtitle507">I know, right?</p>
<p begin="22693087500t" end="22716865003t" region="region.after" style="defaultStyle" xml:id="subtitle508">Can't get two finer reviews than that.</p>
<p begin="22718535005t" end="22757322503t" region="region.after" style="defaultStyle" xml:id="subtitle509"><span style="defaultStyle_2">-How much pressure left in the air tanks?</span><br/><span style="defaultStyle_2">-Down to 800 pounds, sir.</span></p>
<p begin="22758992506t" end="22794857501t" region="region.after" style="defaultStyle" xml:id="subtitle510"><span style="defaultStyle_2">-Secure aft to group below.</span><br/><span style="defaultStyle_2">-Secure aft to group.</span></p>
<p begin="22848665005t" end="22874937501t" region="region.after" style="defaultStyle" xml:id="subtitle511">-It's the boss.<br/>-At this hour?</p>
<p begin="22876607502t" end="22914560001t" region="region.after" style="defaultStyle" xml:id="subtitle512">It's never too late for congratulations.</p>
<p begin="22938337505t" end="22968785005t" region="region.after" style="defaultStyle" xml:id="subtitle513">Cliff, Jesus, you're still at the office.</p>
<p begin="22970455006t" end="22995057501t" region="region.after" style="defaultStyle" xml:id="subtitle514"><span style="defaultStyle_2">You ran a commercial?</span></p>
<p begin="22996727502t" end="23033427500t" region="region.after" style="defaultStyle" xml:id="subtitle515">Yeah, and oh, my God, let me tell you:<br/>The response has been--</p>
<p begin="23035097501t" end="23045525001t" region="region.after" style="defaultStyle" xml:id="subtitle516"><span style="defaultStyle_2">You ran a commercial...</span></p>
<p begin="23047195003t" end="23075555001t" region="region.after" style="defaultStyle" xml:id="subtitle517">...without showing it to me<br/>and consulting me and my partners.</p>
<p begin="23077225003t" end="23098497505t" region="region.after" style="defaultStyle" xml:id="subtitle518">Did you actually think<br/>that was gonna fly?</p>
<p begin="23100167506t" end="23123517500t" region="region.after" style="defaultStyle" xml:id="subtitle519"><span style="defaultStyle_2">I was planning on telling you</span><br/><span style="defaultStyle_2">in the morning.</span></p>
<p begin="23125187501t" end="23148130003t" region="region.after" style="defaultStyle" xml:id="subtitle520">-The day after it aired?<br/><span style="defaultStyle_2">-I only ran it once.</span></p>
<p begin="23149800006t" end="23189005005t" region="region.after" style="defaultStyle" xml:id="subtitle521">Just in one small market.<br/>It was kind of an experiment, all right?</p>
<p begin="23190675006t" end="23215695001t" region="region.after" style="defaultStyle" xml:id="subtitle522">Kind of under the radar.</p>
<p begin="23217365003t" end="23255317501t" region="region.after" style="defaultStyle" xml:id="subtitle523">And in all fairness, you did tell me<br/>client outreach was my department.</p>
<p begin="23256987502t" end="23269085005t" region="region.after" style="defaultStyle" xml:id="subtitle524"><span style="defaultStyle_2">Don't be disingenuous.</span></p>
<p begin="23270755006t" end="23303697500t" region="region.after" style="defaultStyle" xml:id="subtitle525"><span style="defaultStyle_2">This commercial,</span><br/><span style="defaultStyle_2">I take it my firm's name is mentioned?</span></p>
<p begin="23315795001t" end="23339155005t" region="region.after" style="defaultStyle" xml:id="subtitle526">Yes. Yeah.</p>
<p begin="23340825006t" end="23365845001t" region="region.after" style="defaultStyle" xml:id="subtitle527">Jesus. Howard said<br/>you were a little eccentric...</p>
<p begin="23367515003t" end="23389205005t" region="region.after" style="defaultStyle" xml:id="subtitle528">...he didn't tell me<br/>you're a goddamn arsonist.</p>
<p begin="23400050006t" end="23432167508t" region="region.after" style="defaultStyle" xml:id="subtitle529">Cliff, to be fair, I don't think....</p>
<p begin="23451352507t" end="23490140006t" region="region.after" style="defaultStyle" xml:id="subtitle530">I apologize if there was any misreading<br/>of the situation on my part.</p>
<p begin="23491810007t" end="23512665008t" region="region.after" style="defaultStyle" xml:id="subtitle531">But there's<br/>a very positive headline here.</p>
<p begin="23514325000t" end="23543937500t" region="region.after" style="defaultStyle" xml:id="subtitle532">We got 103 phone calls today...</p>
<p begin="23545607501t" end="23584812500t" region="region.after" style="defaultStyle" xml:id="subtitle533">...off a measly $700 ad buy.<br/>Now, that kind of return on investment...</p>
<p begin="23586482502t" end="23611512507t" region="region.after" style="defaultStyle" xml:id="subtitle534">-...you can't--<br/><span style="defaultStyle_2">-Tomorrow morning, 8:00, my office...</span></p>
<p begin="23613182508t" end="23634027500t" region="region.after" style="defaultStyle" xml:id="subtitle535">...with the partners.<br/>We wanna see this thing.</p>
<p begin="23635697501t" end="23667815003t" region="region.after" style="defaultStyle" xml:id="subtitle536">Cliff, when you see this,<br/>I know you'll--</p>
<p begin="23714525000t" end="23731632507t" region="region.after" style="defaultStyle" xml:id="subtitle537">Yeah, Cliff.</p>
<p begin="23748312503t" end="23762497508t" region="region.after" style="defaultStyle" xml:id="subtitle538">Thank you.</p>
<p begin="23764157500t" end="23779177505t" region="region.after" style="defaultStyle" xml:id="subtitle539">Yeah, you too.</p>
<p begin="23780847506t" end="23803780000t" region="region.after" style="defaultStyle" xml:id="subtitle540">Okay, see you.</p>
<p begin="23819635005t" end="23835062500t" region="region.after" style="defaultStyle" xml:id="subtitle541">Golden boy.</p>
<p begin="23843820000t" end="23860092506t" region="region.after" style="defaultStyle" xml:id="subtitle542">That's me.</p>
<p begin="23913890000t" end="23943512508t" region="region.after" style="defaultStyle" xml:id="subtitle543">So what did I miss?<br/>Anything blow up yet?</p>
<p begin="24577472502t" end="24599997505t" region="region.after" style="defaultStyle" xml:id="subtitle544">Feeling cautious?</p>
<p begin="24626687501t" end="24652970007t" region="region.after" style="defaultStyle" xml:id="subtitle545">You gonna tell me<br/>what we're doing here?</p>
<p begin="24667562502t" end="24688417502t" region="region.after" style="defaultStyle" xml:id="subtitle546">-I've got a problem.<br/>-Okay.</p>
<p begin="24690087505t" end="24720952506t" region="region.after" style="defaultStyle" xml:id="subtitle547">This problem, I can't solve it myself.</p>
<p begin="24722622507t" end="24764332508t" region="region.after" style="defaultStyle" xml:id="subtitle548">This problem, is it a who or what?</p>
<p begin="24789352503t" end="24806867501t" region="region.after" style="defaultStyle" xml:id="subtitle549">There's a guy.</p>
<p begin="24825217500t" end="24854422508t" region="region.after" style="defaultStyle" xml:id="subtitle550">I need him to go away.</p>
</div>
</body>
</tt>
